MANIFEST.in
README.rst
setup.py
bin/metatools_convert
bin/metatools_download
metatools_ncbi/__init__.py
metatools_ncbi/biosample.py
metatools_ncbi/convert_to_biosample.py
metatools_ncbi.egg-info/PKG-INFO
metatools_ncbi.egg-info/SOURCES.txt
metatools_ncbi.egg-info/dependency_links.txt
metatools_ncbi.egg-info/not-zip-safe
metatools_ncbi.egg-info/requires.txt
metatools_ncbi.egg-info/top_level.txt