Metadata-Version: 1.1
Name: metatools-ncbi
Version: 0.2.1
Summary: Download biosample and SRA runinfo metadata from NCBI
Home-page: http://github.com/farhat-lab/metatools_ncbi
Author: Luca Freschi
Author-email: l.freschi@gmail.com
License: LGPLv3
Keywords: ncbi download metadata biosample runinfo
Platform: UNKNOWN
Classifier: Development Status :: 4 - Beta
Classifier: Environment :: Console
Classifier: License :: OSI Approved :: GNU Lesser General Public License v3 (LGPLv3)
Classifier: Operating System :: POSIX :: Linux
Classifier: Programming Language :: Python :: 3
Classifier: Topic :: Scientific/Engineering :: Bio-Informatics
